MANIFEST.in
README.rst
setup.py
pylint_patcher/__init__.py
pylint_patcher/_version.py
pylint_patcher/differ.py
pylint_patcher/main.py
pylint_patcher/main_gui.py
pylint_patcher/patcher.py
pylint_patcher/utils.py
pylint_patcher.egg-info/PKG-INFO
pylint_patcher.egg-info/SOURCES.txt
pylint_patcher.egg-info/dependency_links.txt
pylint_patcher.egg-info/entry_points.txt
pylint_patcher.egg-info/requires.txt
pylint_patcher.egg-info/top_level.txt
pylint_patcher.egg-info/zip-safe
pylint_patcher/external/__init__.py
pylint_patcher/external/pylint/__init__.py
pylint_patcher/external/pylint/gui.py