Metadata-Version: 1.1
Name: pylint-patcher
Version: 0.3.1
Summary: Pylint addon to store lint exceptions in a patchfile.
Home-page: https://github.com/sneakypete81/pylint-patcher
Author: Pete Burgers
Author-email: UNKNOWN
License: GPL 2.0
Keywords: pylint-patcher,pylint_patcher,pylint,pylint-patcher-gui,pylint_patcher_gui,patch,patchfile
Platform: UNKNOWN
Classifier: Development Status :: 4 - Beta
Classifier: Intended Audience :: Developers
Classifier: License :: OSI Approved :: GNU General Public License v2 (GPLv2)
Classifier: Operating System :: OS Independent
Classifier: Programming Language :: Python
Classifier: Topic :: Software Development :: Quality Assurance
Classifier: Topic :: Utilities
